Metadata-Version: 2.1
Name: tmflow
Version: 0.5.0
Summary: Taylor map flow is a package for a 'flowly' construction and learning of polynomial neural networks (PNN) for time-evolving process prediction
Home-page: https://github.com/PNN-Lab/tmflow
Author: PNN Lab
Author-email: golovkina.a@gmail.com
Project-URL: Bug Reports, https://github.com/PNN-Lab/tmflow/issues
Project-URL: Source, https://github.com/PNN-Lab/tmflow
Project-URL: Examples, https://github.com/PNN-Lab/tmflow/tree/main/examples
Project-URL: Changelog, https://github.com/PNN-Lab/tmflow/blob/main/CHANGELOG.md
Keywords: PNN,Taylor,ODE,TensorFlow
Classifier: Development Status :: 3 - Alpha
Classifier: Intended Audience :: Science/Research
Classifier: Intended Audience :: Developers
Classifier: Topic :: Scientific/Engineering :: Artificial Intelligence
Classifier: Topic :: Scientific/Engineering :: Mathematics
Classifier: Topic :: Scientific/Engineering :: Physics
Classifier: Topic :: Software Development :: Libraries :: Python Modules
Classifier: License :: OSI Approved :: Apache Software License
Classifier: Programming Language :: Python :: 3
Classifier: Programming Language :: Python :: 3.9
Classifier: Programming Language :: Python :: 3.10
Classifier: Programming Language :: Python :: 3 :: Only
Requires-Python: >=3.9, <4
License-File: LICENSE
Requires-Dist: tensorflow (<2.12,>=2.8)
Requires-Dist: scipy (<1.11,>=1.6)
Requires-Dist: numpy (<1.24,>=1.20)
Requires-Dist: sympy (~=1.8)
Requires-Dist: numba (<0.57,>=0.55)
Provides-Extra: examples
Requires-Dist: matplotlib (<3.4,>=3.3) ; extra == 'examples'
Requires-Dist: pandas (<1.6,>=1.3) ; extra == 'examples'
Requires-Dist: scikit-learn (<1.3,>=0.24) ; extra == 'examples'
